vxn/__init__.py
vxn/__main__.py
vxn/file_utils.py
vxn/vxn.py
vxn/formats/__init__.py
vxn/formats/audioformat.py
vxn/formats/mpc.py
vxn/formats/ms_adpcm.py
vxn/formats/ms_ima_adpcm.py
vxn/formats/pcm.py
vxn/formats/wav.py
vxn_py-1.0.3.dist-info/licenses/LICENSE
vxn_py-1.0.3.dist-info/METADATA
vxn_py-1.0.3.dist-info/WHEEL
vxn_py-1.0.3.dist-info/entry_points.txt
vxn_py-1.0.3.dist-info/top_level.txt
vxn_py-1.0.3.dist-info/RECORD
