Metadata-Version: 2.4
Name: vxn-py
Version: 1.0.3
Summary: A python script for decoding Gameloft .vxn files.
Author: ego-lay-atman-bay
License: GNU GENERAL PUBLIC LICENSE
Project-URL: Homepage, https://github.com/ego-lay-atman-bay/vxn-py
Project-URL: Bug Tracker, https://github.com/ego-lay-atman-bay/vxn-py/issues
Classifier: Programming Language :: Python :: 3
Classifier: License :: OSI Approved :: GNU General Public License v3 (GPLv3)
Classifier: Operating System :: OS Independent
Requires-Python: >=3.10
License-File: LICENSE
Requires-Dist: dataclasses-struct
Provides-Extra: filetype
Requires-Dist: filetype; extra == "filetype"
Dynamic: license-file
